WhaleWisdom/__init__.py
WhaleWisdom/main.py
WhaleWisdom/Common/__init__.py
WhaleWisdom/Common/npd_data.py
WhaleWisdom/Common/py_whale_wisdom.py
WhaleWisdom/FundHoldings/__init__.py
WhaleWisdom/FundHoldings/report_builder.py
WhaleWisdom/FundHoldings/report_data.py
npd_whale_wisdom-0.2.4.dist-info/LICENSE
npd_whale_wisdom-0.2.4.dist-info/METADATA
npd_whale_wisdom-0.2.4.dist-info/WHEEL
npd_whale_wisdom-0.2.4.dist-info/top_level.txt
npd_whale_wisdom-0.2.4.dist-info/RECORD
