Metadata-Version: 2.1
Name: npd-whale-wisdom
Version: 0.2.4
Summary: Library for making use of Whale Wisdom API
Home-page: https://NPDGroup@dev.azure.com/NPDGroup/NPDFinancialServices/_git/WhaleWisdom
Author: Max Leonard
Author-email: maxhleonard@gmail.com
License: UNKNOWN
Platform: UNKNOWN
Classifier: Programming Language :: Python :: 3
Classifier: License :: OSI Approved :: MIT License
Classifier: Operating System :: OS Independent
Requires-Python: >=3.6
License-File: LICENSE
Requires-Dist: pandas
Requires-Dist: XlsxWriter
Requires-Dist: certifi
Requires-Dist: requests
Requires-Dist: beautifulsoup4
Requires-Dist: matplotlib
